{
  "operationId": "addGroupMembers",
  "tags": [
    "Groups"
  ],
  "summary": "Add users to a group",
  "description": "Requires Manage/Group workspace permission.",
  "requestBody": {
    "required": true,
    "content": {
      "application/json": {
        "schema": {
          "type": "object",
          "required": [
            "groupId",
            "userIds"
          ],
          "properties": {
            "groupId": {
              "type": "string",
              "format": "uuid",
              "description": "ID of the group to add users to."
            },
            "userIds": {
              "type": "array",
              "minItems": 1,
              "maxItems": 50,
              "items": {
                "type": "string",
                "format": "uuid"
              },
              "description": "User IDs to add to the group. 1–50 per request. Users already in the group are skipped."
            }
          }
        }
      }
    }
  },
  "responses": {
    "200": {
      "description": "Members added",
      "content": {
        "application/json": {
          "schema": {
            "type": "object",
            "properties": {
              "data": {
                "description": "Response payload"
              },
              "success": {
                "type": "boolean",
                "examples": [
                  true
                ]
              },
              "status": {
                "type": "integer",
                "examples": [
                  200
                ]
              }
            }
          }
        }
      }
    },
    "400": {
      "description": "Validation error",
      "content": {
        "application/json": {
          "schema": {
            "type": "object",
            "properties": {
              "statusCode": {
                "type": "integer"
              },
              "message": {
                "oneOf": [
                  {
                    "type": "string"
                  },
                  {
                    "type": "array",
                    "items": {
                      "type": "string"
                    }
                  }
                ]
              },
              "error": {
                "type": "string"
              }
            }
          }
        }
      }
    },
    "403": {
      "description": "Forbidden",
      "content": {
        "application/json": {
          "schema": {
            "type": "object",
            "properties": {
              "statusCode": {
                "type": "integer"
              },
              "message": {
                "oneOf": [
                  {
                    "type": "string"
                  },
                  {
                    "type": "array",
                    "items": {
                      "type": "string"
                    }
                  }
                ]
              },
              "error": {
                "type": "string"
              }
            }
          }
        }
      }
    }
  }
}